optimalpdb/__init__.py
optimalpdb/main.py
optimalpdb-1.0.dist-info/METADATA
optimalpdb-1.0.dist-info/WHEEL
optimalpdb-1.0.dist-info/top_level.txt
optimalpdb-1.0.dist-info/RECORD
