Metadata-Version: 2.1
Name: optimalpdb
Version: 1.0
Summary: This package gets 3D structures by taking UniProt ID(s) as input, figures out the currently available PDB structures that are experimentally validated, and chooses the best structure based on lowest resolution (A value). Then it extracts PDB ID(s) that should be retrieved and stores it in a CSV file.
Author: Waqar Hanif
Requires-Dist: requests
